{
	"configurations" : 
	[
		{
			"directories" : 
			[
				{
					"build" : ".",
					"jsonFile" : "directory-.-Debug-f5ebdc15457944623624.json",
					"minimumCMakeVersion" : 
					{
						"string" : "3.16"
					},
					"projectIndex" : 0,
					"source" : ".",
					"targetIndexes" : 
					[
						0
					]
				}
			],
			"name" : "Debug",
			"projects" : 
			[
				{
					"directoryIndexes" : 
					[
						0
					],
					"name" : "Viewer",
					"targetIndexes" : 
					[
						0
					]
				}
			],
			"targets" : 
			[
				{
					"directoryIndex" : 0,
					"id" : "viewer::@6890427a1f51a3e7e1df",
					"jsonFile" : "target-viewer-Debug-669ff0e0b66d0dfcbbf7.json",
					"name" : "viewer",
					"projectIndex" : 0
				}
			]
		}
	],
	"kind" : "codemodel",
	"paths" : 
	{
		"build" : "/workspaces/make_usd_great_again/build",
		"source" : "/workspaces/make_usd_great_again/src/Viewer"
	},
	"version" : 
	{
		"major" : 2,
		"minor" : 6
	}
}
